odoo8_addon_website_menu_multilang-8.0.0.1.0.99.dev10-py3.8-nspkg.pth
odoo_addons/website_menu_multilang/__init__.py
odoo_addons/website_menu_multilang/__openerp__.py
odoo_addons/website_menu_multilang/i18n/de.po
odoo_addons/website_menu_multilang/i18n/el_GR.po
odoo_addons/website_menu_multilang/i18n/es.po
odoo_addons/website_menu_multilang/i18n/fr.po
odoo_addons/website_menu_multilang/i18n/it.po
odoo_addons/website_menu_multilang/i18n/pt_BR.po
odoo_addons/website_menu_multilang/i18n/ru.po
odoo_addons/website_menu_multilang/i18n/sl.po
odoo_addons/website_menu_multilang/i18n/website_menu_multilang.pot
odoo_addons/website_menu_multilang/model/__init__.py
odoo_addons/website_menu_multilang/model/website.py
odoo_addons/website_menu_multilang/static/description/icon.png
odoo_addons/website_menu_multilang/view/website.xml
odoo8_addon_website_menu_multilang-8.0.0.1.0.99.dev10.dist-info/METADATA
odoo8_addon_website_menu_multilang-8.0.0.1.0.99.dev10.dist-info/WHEEL
odoo8_addon_website_menu_multilang-8.0.0.1.0.99.dev10.dist-info/namespace_packages.txt
odoo8_addon_website_menu_multilang-8.0.0.1.0.99.dev10.dist-info/top_level.txt
odoo8_addon_website_menu_multilang-8.0.0.1.0.99.dev10.dist-info/RECORD
