Metadata-Version: 2.1
Name: odoo8-addon-website-menu-multilang
Version: 8.0.0.1.0.99.dev10
Summary: Website Menu Multilanguage
Home-page: http://www.versada.lt
Author: Versada UAB,Odoo Community Association (OCA)
Author-email: support@odoo-community.org
License: UNKNOWN
Platform: UNKNOWN
Classifier: Programming Language :: Python
Classifier: Framework :: Odoo
Classifier: Framework :: Odoo :: 8.0
Requires-Python: ~=2.7
Requires-Dist: odoo (<9.0a,>=8.0a)
